nlp_lab_pkg/__init__.py
nlp_lab_pkg_i061_oct25-0.0.2.dist-info/METADATA
nlp_lab_pkg_i061_oct25-0.0.2.dist-info/WHEEL
nlp_lab_pkg_i061_oct25-0.0.2.dist-info/top_level.txt
nlp_lab_pkg_i061_oct25-0.0.2.dist-info/RECORD
