Metadata-Version: 2.1
Name: nlp-lab-pkg-i061-oct25
Version: 0.0.2
Summary: NLP Lab utilities for tokenization, stemming, and tagging.
Home-page: https://github.com/jindsaini2013/nlp-lab-pkg-i061.git
Author: Jind Saini
Author-email: jindsaini20@gmail.com
Classifier: Programming Language :: Python :: 3
Classifier: License :: OSI Approved :: MIT License
Classifier: Operating System :: OS Independent
Requires-Python: >=3.6
Requires-Dist: nltk >=3.5
